AUTHORS.rst
CONTRIBUTING.rst
HISTORY.rst
LICENSE
MANIFEST.in
README.rst
setup.py
sysenv/__init__.py
sysenv/data.py
sysenv.egg-info/PKG-INFO
sysenv.egg-info/SOURCES.txt
sysenv.egg-info/dependency_links.txt
sysenv.egg-info/not-zip-safe
sysenv.egg-info/top_level.txt