Metadata-Version: 1.0
Name: sysenv
Version: 0.1.0
Summary: Simple handling of system environment variables for application deployment.
Home-page: https://gitthub.com/bennylope/sysenv
Author: Ben Lopatin
Author-email: ben@wellfire.co
License: BSD
Keywords: sysenv
Platform: UNKNOWN
Classifier: Development Status :: 2 - Pre-Alpha
Classifier: Intended Audience :: Developers
Classifier: License :: OSI Approved :: BSD License
Classifier: Natural Language :: English
Classifier: Programming Language :: Python :: 2
Classifier: Programming Language :: Python :: 2.6
Classifier: Programming Language :: Python :: 2.7
Classifier: Programming Language :: Python :: 3
Classifier: Programming Language :: Python :: 3.3
